lollipop_hypothesis/__init__.py
lollipop_hypothesis/strategy.py
lollipop_hypothesis-0.2.dist-info/DESCRIPTION.rst
lollipop_hypothesis-0.2.dist-info/METADATA
lollipop_hypothesis-0.2.dist-info/RECORD
lollipop_hypothesis-0.2.dist-info/WHEEL
lollipop_hypothesis-0.2.dist-info/metadata.json
lollipop_hypothesis-0.2.dist-info/top_level.txt
