Metadata-Version: 2.0
Name: lollipop-hypothesis
Version: 0.2
Summary: Library to generate random test data using Hypothesis based on Lollipop schema
Home-page: https://github.com/maximkulkin/lollipop-hypothesis
Author: Maxim Kulkin
Author-email: maxim.kulkin@gmail.com
License: MIT
Keywords: lollipop,hypothesis
Platform: UNKNOWN
Classifier: Development Status :: 3 - Alpha
Classifier: Intended Audience :: Developers
Classifier: License :: OSI Approved :: MIT License
Classifier: Programming Language :: Python :: 2
Classifier: Programming Language :: Python :: 2.7
Classifier: Programming Language :: Python :: 3
Classifier: Programming Language :: Python :: 3.3
Classifier: Programming Language :: Python :: 3.4
Classifier: Programming Language :: Python :: 3.5
Classifier: Programming Language :: Python :: 3.6
Classifier: Programming Language :: Python :: Implementation :: CPython
Classifier: Programming Language :: Python :: Implementation :: PyPy
Requires-Dist: hypothesis (>=3.8)
Requires-Dist: hypothesis[datetime]
Requires-Dist: lollipop (>=1.1.3)
Requires-Dist: six (>=1.10)
Provides-Extra: regex
Requires-Dist: hypothesis-regex; extra == 'regex'
